ghpr.py
src/__init__.py
src/github/__init__.py
src/github/github.py
src/helpers/__init__.py
src/helpers/formatHelper.py
src/helpers/githubHelper.py
ghpr-1.0.0.dist-info/LICENSE
ghpr-1.0.0.dist-info/METADATA
ghpr-1.0.0.dist-info/WHEEL
ghpr-1.0.0.dist-info/entry_points.txt
ghpr-1.0.0.dist-info/top_level.txt
ghpr-1.0.0.dist-info/RECORD
