Metadata-Version: 2.1
Name: ghpr
Version: 1.0.0
Summary: Project to get data from github pull requests
Home-page: https://github.com/vinaymavi/github-pr-data
Author: VinayMavi
Author-email: vinaymavi@gmail.com
License: MIT
Project-URL: Bug Tracker, https://github.com/vinaymavi/github-pr-data/issues
Platform: UNKNOWN
Requires-Python: >=3.6
License-File: LICENSE
Requires-Dist: click (==8.0.1)
Requires-Dist: PyGithub (==1.55)
Requires-Dist: pyperclip (==1.8.2)
Requires-Dist: tabulate (==0.8.9)
